latex_tools/__init__.py
latex_tools/latex_generator.py
petonzxc_latex_tools-0.2.1.dist-info/METADATA
petonzxc_latex_tools-0.2.1.dist-info/WHEEL
petonzxc_latex_tools-0.2.1.dist-info/top_level.txt
petonzxc_latex_tools-0.2.1.dist-info/RECORD
