Metadata-Version: 2.4
Name: petonzxc-latex-tools
Version: 0.2.1
Summary: Simple LaTeX table and image generation tools
Author: Petr Tyapkin
Requires-Python: >=3.8
